CHANGES.txt
LICENSE
MANIFEST.in
README.rst
setup.cfg
setup.py
nose_mongoengine/__init__.py
nose_mongoengine.egg-info/PKG-INFO
nose_mongoengine.egg-info/SOURCES.txt
nose_mongoengine.egg-info/dependency_links.txt
nose_mongoengine.egg-info/entry_points.txt
nose_mongoengine.egg-info/requires.txt
nose_mongoengine.egg-info/top_level.txt
nose_mongoengine.egg-info/zip-safe