Metadata-Version: 1.1
Name: nose-mongoengine
Version: 0.2.2
Summary: A nose plugin to facilitate the creation of automated tests that access Mongo Engine structures.
Home-page: http://github.com/mbanton/nose-mongoengine/
Author: Marcelo Anton
Author-email: marceloanton@gmail.com
License: BSD-derived
Download-URL: http://github.com/mbanton/nose-mongoengine/tarball/master
Platform: any
Classifier: Environment :: Plugins
Classifier: Intended Audience :: Developers
Classifier: Programming Language :: Python
Classifier: Operating System :: OS Independent
Classifier: Topic :: Internet :: WWW/HTTP
